fastavro_gen/__init__.py
fastavro_gen/__main__.py
fastavro_gen/from_dict.py
fastavro_gen/models.py
fastavro_gen/py.typed
fastavro_gen/type_gen.py
fastavro_gen-0.0.3.dist-info/LICENSE
fastavro_gen-0.0.3.dist-info/METADATA
fastavro_gen-0.0.3.dist-info/WHEEL
fastavro_gen-0.0.3.dist-info/entry_points.txt
fastavro_gen-0.0.3.dist-info/top_level.txt
fastavro_gen-0.0.3.dist-info/RECORD
