Metadata-Version: 2.1
Name: fastavro-gen
Version: 0.0.3
Summary: Generation of classes from Avro schemas
Home-page: https://github.com/gudjonragnar/fastavro-gen
Author: Guðjón Ragnar Brynjarsson
License: MIT
Platform: UNKNOWN
Requires-Python: >=3.8
Requires-Dist: fastavro (>=1.3.0)
Requires-Dist: black
Provides-Extra: codecs
Requires-Dist: python-snappy ; extra == 'codecs'
Requires-Dist: zstandard ; extra == 'codecs'
Requires-Dist: lz4 ; extra == 'codecs'
Provides-Extra: lz4
Requires-Dist: lz4 ; extra == 'lz4'
Provides-Extra: snappy
Requires-Dist: python-snappy ; extra == 'snappy'
Provides-Extra: zstandard
Requires-Dist: zstandard ; extra == 'zstandard'
